markl/__init__.py
markl/config.py
markl/get_tsxs.py
markl/mark.py
markl/rollback.py
markl-0.0.4.dist-info/LICENSE
markl-0.0.4.dist-info/METADATA
markl-0.0.4.dist-info/WHEEL
markl-0.0.4.dist-info/entry_points.txt
markl-0.0.4.dist-info/top_level.txt
markl-0.0.4.dist-info/RECORD
